djangmx/__init__.py
djangmx-0.0.6.dist-info/LICENSE
djangmx-0.0.6.dist-info/METADATA
djangmx-0.0.6.dist-info/WHEEL
djangmx-0.0.6.dist-info/top_level.txt
djangmx-0.0.6.dist-info/RECORD
