Metadata-Version: 2.1
Name: djangmx
Version: 0.0.6
Summary: handles communication between AMX masters and django
Home-page: https://github.com/logantv/djangmx
Author: Logan Vaughn
License: UNKNOWN
Project-URL: Bug Tracker, https://github.com/logantv/djangmx/issues
Platform: UNKNOWN
Classifier: Programming Language :: Python :: 3
Classifier: License :: OSI Approved :: MIT License
Classifier: Operating System :: OS Independent
Requires-Python: >=3.6
License-File: LICENSE
